pytest_cppython/__init__.py
pytest_cppython/fixture_data/__init__.py
pytest_cppython/fixture_data/configuration.py
pytest_cppython/fixture_data/cppython.py
pytest_cppython/fixture_data/pep621.py
pytest_cppython/fixtures.py
pytest_cppython/mock.py
pytest_cppython/plugin.py
pytest_cppython/py.typed
pytest_cppython-0.3.0.dist-info/WHEEL
pytest_cppython-0.3.0.dist-info/METADATA
pytest_cppython-0.3.0.dist-info/license_files/LICENSE.md
pytest_cppython-0.3.0.dist-info/RECORD
