Metadata-Version: 2.1
Name: pytest-cppython
Version: 0.3.0
Summary: A pytest plugin that imports CPPython testing types
License: MIT
Author-email: Synodic Software <contact@synodic.software>
Requires-Python: >=3.10
Requires-Dist: cppython-core>=0.4.1.dev13
Requires-Dist: pydantic>=1.9.2
Project-URL: homepage, https://github.com/Synodic-Software/Pytest-CPPython
Project-URL: repository, https://github.com/Synodic-Software/Pytest-CPPython
